<?xml version="1.0" encoding="utf-8" ?>
<Defs>

  <HediffDef ParentName="InjuryBase">
    <defName>TissueHypoxia</defName>
    <label>组织缺氧</label>
    <labelNoun>缺氧组织</labelNoun>
    <description>由于严重缺氧和代谢性酸中毒导致的局部组织损伤。像冻伤一样，它会持续破坏组织扣减血量，如果不及早恢复血液循环，会导致部位永久脱落。</description>
    <hediffClass>EmergencyExpanded.Hediff_TissueHypoxia</hediffClass>
    <initialSeverity>3.0</initialSeverity> 
    <injuryProps>
      <painPerSeverity>0.015</painPerSeverity>
      <averagePainPerSeverityPermanent>0.005</averagePainPerSeverityPermanent>
      <canMerge>true</canMerge> 
      <destroyedLabel>组织坏死</destroyedLabel>
      <destroyedOutLabel>组织坏死</destroyedOutLabel>
    </injuryProps>
  </HediffDef>

  <HediffDef>
    <defName>MetabolicAcidosis</defName>
    <label>代谢性酸中毒</label>
    <description>因组织灌注不足导致的酸碱平衡崩盘。系统一旦崩溃，酸中毒将持续恶化啃食机体。发展到晚期时，会引发不可逆的多脏器缺血衰竭并导致死亡。</description>
    <hediffClass>EmergencyExpanded.Hediff_MetabolicAcidosis</hediffClass>
    <defaultLabelColor>(0.8, 0.8, 0.3)</defaultLabelColor>
    <maxSeverity>1.0</maxSeverity> 
    <initialSeverity>0.1</initialSeverity>
    <makesSickThought>true</makesSickThought>
    <tendable>true</tendable>
    <comps>
      <li Class="HediffCompProperties_TendDuration">
        <baseTendDurationHours>12</baseTendDurationHours>
        <severityPerDayTended>-2.0</severityPerDayTended> 
      </li>
      <li Class="EmergencyExpanded.HediffCompProperties_Acidosis">
        <severityIncreasePerDay>2.0</severityIncreasePerDay>
        <severityDecreasePerDay>1.2</severityDecreasePerDay>
        <bloodPumpingThreshold>0.50</bloodPumpingThreshold>
        <breathingThreshold>0.50</breathingThreshold>
      </li>
    </comps>
    <stages>
      <li>
        <label>轻度</label>
        <capMods>
          <li><capacity>Breathing</capacity><offset>-0.2</offset></li>
          <li><capacity>BloodPumping</capacity><offset>-0.2</offset></li> 
        </capMods>
      </li>
      <li>
        <minSeverity>0.2</minSeverity>
        <label>中度</label>
        <painOffset>0.1</painOffset>
        <capMods>
          <li><capacity>Consciousness</capacity><offset>-0.2</offset></li>
          <li><capacity>BloodPumping</capacity><offset>-0.2</offset></li> 
        </capMods>
      </li>
      <li>
        <minSeverity>0.5</minSeverity>
        <label>重度</label>
        <lifeThreatening>true</lifeThreatening>
        <painOffset>0.25</painOffset>
        <capMods>
          <li><capacity>Consciousness</capacity><setMax>0.5</setMax></li>
          <li><capacity>BloodPumping</capacity><setMax>0.5</setMax></li> 
        </capMods>
        <hediffGivers>
          <li Class="HediffGiver_Random">
            <hediff>VentricularFibrillation</hediff>
            <mtbDays>0.03</mtbDays> 
            <partsToAffect>
              <li>Heart</li>
            </partsToAffect>
          </li>
        </hediffGivers>
      </li>
      <li>
        <minSeverity>0.95</minSeverity>
        <label>极重度 - 崩溃边缘</label> 
        <lifeThreatening>true</lifeThreatening>
        <painOffset>0.40</painOffset>
        <capMods>
          <li><capacity>Consciousness</capacity><setMax>0.3</setMax></li>
          <li><capacity>BloodPumping</capacity><setMax>0.3</setMax></li>
        </capMods>
        <hediffGivers>
          <li Class="HediffGiver_Random">
            <hediff>VentricularFibrillation</hediff>
            <mtbDays>0.1</mtbDays> 
            <partsToAffect>
              <li>Heart</li>
            </partsToAffect>
          </li>
        </hediffGivers>
      </li>
    </stages>
  </HediffDef>

  <HediffDef>
    <defName>VentricularFibrillation</defName>
    <label>心肌梗死</label>
    <description>由于冠状动脉急性阻塞导致心肌大面积缺血缺氧坏死。会引发毁灭性的泵血与循环功能衰竭，如不及时除颤与抢救，将导致全身多脏器缺氧衰竭而死亡。</description>
    <hediffClass>EmergencyExpanded.Hediff_VentricularFibrillation</hediffClass>
    <defaultLabelColor>(0.9, 0.2, 0.2)</defaultLabelColor>
    <initialSeverity>0.01</initialSeverity>
    <tendable>true</tendable> 
    <comps>
      <li Class="HediffCompProperties_SeverityPerDay">
        <severityPerDay>8.0</severityPerDay> 
      </li>
      <li Class="HediffCompProperties_TendDuration">
        <baseTendDurationHours>1.5</baseTendDurationHours> 
        <severityPerDayTended>-10.0</severityPerDayTended> 
      </li>
    </comps>
    <stages>
      <li>
        <label>室颤</label>
        <lifeThreatening>true</lifeThreatening>
        <capMods>
          <li><capacity>BloodPumping</capacity><setMax>0.10</setMax></li> 
          <li><capacity>Consciousness</capacity><setMax>0.10</setMax></li>
        </capMods>
      </li>
      <li>
        <minSeverity>0.60</minSeverity>
        <label>心跳骤停</label>
        <lifeThreatening>true</lifeThreatening>
        <capMods>
          <li><capacity>BloodPumping</capacity><setMax>0.01</setMax></li> 
          <li><capacity>Breathing</capacity><setMax>0.01</setMax></li>
          <li><capacity>Consciousness</capacity><setMax>0.01</setMax></li>
        </capMods>
      </li>
    </stages>
  </HediffDef>

  <HediffDef>
    <defName>CerebralHypoxia</defName>
    <label>脑缺氧</label>
    <description>大脑供血或供氧不足导致的急性神经系统损伤。随着缺氧加剧，意识会逐渐丧失，并伴随不可逆的脑部器质性损伤。如果达到极限，将导致彻底的脑死亡。</description>
    <hediffClass>EmergencyExpanded.Hediff_CerebralHypoxia</hediffClass>
    <defaultLabelColor>(0.6, 0.4, 0.8)</defaultLabelColor>
    <maxSeverity>1.0</maxSeverity> 
    <initialSeverity>0.05</initialSeverity>
    <comps>
      <li Class="EmergencyExpanded.HediffCompProperties_CerebralHypoxia"/>
    </comps>
    <stages>
      <li>
        <label>轻度 - 意识丧失并倒地</label>
        <capMods>
          <li><capacity>Consciousness</capacity><setMax>0.10</setMax></li>
        </capMods>
      </li>
      <li>
        <minSeverity>0.25</minSeverity>
        <label>中度 - 神经紊乱昏迷</label>
        <capMods>
          <li><capacity>Consciousness</capacity><setMax>0.08</setMax></li>
          <li><capacity>Talking</capacity><setMax>0.5</setMax></li>
        </capMods>
      </li>
      <li>
        <minSeverity>0.5</minSeverity>
        <label>重度 - 深度昏迷</label>
        <capMods>
          <li><capacity>Consciousness</capacity><setMax>0.05</setMax></li>
        </capMods>
      </li>
      <li>
        <minSeverity>0.7</minSeverity>
        <label>极重度 - 濒临脑死亡</label>
        <lifeThreatening>true</lifeThreatening>
        <capMods>
          <li><capacity>Consciousness</capacity><setMax>0.01</setMax></li> 
        </capMods>
      </li>
    </stages>
  </HediffDef>

  <HediffDef>
    <defName>HypoxicBrainDamage</defName>
    <label>缺氧性脑损伤</label>
    <description>由于严重脑缺氧导致的不可逆脑组织永久性坏死。这会实质性地且不可逆地摧毁小人的认知、语言和运动运动能力。</description>
    <hediffClass>EmergencyExpanded.Hediff_HypoxicBrainDamage</hediffClass>
    <defaultLabelColor>(0.85, 0.3, 0.3)</defaultLabelColor>
    <maxSeverity>1.0</maxSeverity>
    <isBad>true</isBad>
    <stages>
      <li>
        <label>轻度神经功能缺损</label>
        <capMods>
          <li><capacity>Consciousness</capacity><offset>-0.05</offset></li>
        </capMods>
      </li>
      <li>
        <minSeverity>0.25</minSeverity>
        <label>中度神经功能缺损</label>
        <capMods>
          <li><capacity>Consciousness</capacity><offset>-0.15</offset></li>
          <li><capacity>Talking</capacity><offset>-0.15</offset></li>
          <li><capacity>Moving</capacity><offset>-0.10</offset></li>
        </capMods>
      </li>
      <li>
        <minSeverity>0.55</minSeverity>
        <label>重度偏瘫与失语</label>
        <capMods>
          <li><capacity>Consciousness</capacity><setMax>0.50</setMax></li>
          <li><capacity>Talking</capacity><setMax>0.10</setMax></li>
          <li><capacity>Moving</capacity><setMax>0.30</setMax></li>
        </capMods>
      </li>
      <li>
        <minSeverity>0.85</minSeverity>
        <label>濒临全面脑死亡</label>
        <capMods>
          <li><capacity>Consciousness</capacity><setMax>0.35</setMax></li>
          <li><capacity>Talking</capacity><setMax>0.00</setMax></li>
          <li><capacity>Moving</capacity><setMax>0.05</setMax></li>
        </capMods>
      </li>
    </stages>
  </HediffDef>

  <HediffDef>
    <defName>VegetativeState</defName>
    <label>脑死亡 (植物状态)</label>
    <description>不可逆的广泛性脑神经元坏死。伤者失去了所有高级神经活动，仅依靠脑干维持最基础的心跳和呼吸。如果没有生命维持设备的干预，伤者永远无法醒来。</description>
    <hediffClass>EmergencyExpanded.Hediff_PercentageDisplay</hediffClass>
    <defaultLabelColor>(0.4, 0.4, 0.4)</defaultLabelColor>
    <isBad>true</isBad>
    <stages>
      <li>
        <capMods>
          <li>
            <capacity>Consciousness</capacity>
            <setMax>0.01</setMax> 
          </li>
          <li>
            <capacity>Talking</capacity>
            <setMax>0.0</setMax>
          </li>
          <li>
            <capacity>Moving</capacity>
            <setMax>0.0</setMax>
          </li>
        </capMods>
      </li>
    </stages>
  </HediffDef>

  <HediffDef ParentName="InjuryBase">
    <defName>MassiveBleeding</defName>
    <label>大出血</label>
    <labelNoun>大出血的伤口</labelNoun>
    <description>由于主要血管或动脉破损引发的灾难性大出血。如果不立即就地施加压迫包扎或止血带结扎，伤员将在极短时间内死于失血性休克。</description>
    <hediffClass>Hediff_Injury</hediffClass>
    <defaultLabelColor>(1.0, 0.2, 0.2)</defaultLabelColor> <injuryProps>
      <painPerSeverity>0.02</painPerSeverity>
      <bleedRate>3.0</bleedRate> 
      <canMerge>false</canMerge>
      <destroyedLabel>血管彻底断裂</destroyedLabel>
    </injuryProps>
  </HediffDef>

  <HediffDef>
    <defName>AdrenalineBoost</defName>
    <label>肾上腺素增强</label>
    <description>小人在受到物理创伤或致命危机刺激时分泌的强力肾上腺素，能临时显著增强移动、操作和意识能力，并能够极大削弱身体痛觉感知，防止休克倒地。但在激素消退后会产生强烈的脱水与疲劳反应。</description>
    <hediffClass>EmergencyExpanded.Hediff_PercentageDisplay</hediffClass>
    <defaultLabelColor>(0.9, 0.6, 0.2)</defaultLabelColor>
    <maxSeverity>1.0</maxSeverity>
    <initialSeverity>1.0</initialSeverity>
    <comps>
      <li Class="HediffCompProperties_SeverityPerDay">
        <severityPerDay>-2.0</severityPerDay>
      </li>
      <li Class="EmergencyExpanded.HediffCompProperties_AdrenalineBoost"/>
    </comps>
    <stages>
      <li>
        <label>渐弱消退</label>
        <painFactor>0.95</painFactor>
        <capMods>
          <li><capacity>Consciousness</capacity><offset>0.03</offset></li>
          <li><capacity>Moving</capacity><offset>0.05</offset></li>
          <li><capacity>Manipulation</capacity><offset>0.03</offset></li>
        </capMods>
      </li>
      <li>
        <minSeverity>0.3</minSeverity>
        <label>全身爆发</label>
        <painFactor>0.85</painFactor>
        <capMods>
          <li><capacity>Consciousness</capacity><offset>0.07</offset></li>
          <li><capacity>Moving</capacity><offset>0.10</offset></li>
          <li><capacity>Manipulation</capacity><offset>0.07</offset></li>
        </capMods>
        <statOffsets>
          <MeleeDodgeChance>2.0</MeleeDodgeChance>
          <MeleeHitChance>1.0</MeleeHitChance>
          <ShootingAccuracyPawn>1.0</ShootingAccuracyPawn>
        </statOffsets>
      </li>
      <li>
        <minSeverity>0.7</minSeverity>
        <label>极限应激</label>
        <painFactor>0.80</painFactor>
        <capMods>
          <li><capacity>Consciousness</capacity><offset>0.10</offset></li>
          <li><capacity>Moving</capacity><offset>0.15</offset></li>
          <li><capacity>Manipulation</capacity><offset>0.10</offset></li>
        </capMods>
        <statOffsets>
          <MeleeDodgeChance>5.0</MeleeDodgeChance>
          <MeleeHitChance>2.0</MeleeHitChance>
          <ShootingAccuracyPawn>2.0</ShootingAccuracyPawn>
        </statOffsets>
      </li>
    </stages>
  </HediffDef>

  <HediffDef>
    <defName>AdrenalineCrash</defName>
    <label>肾上腺素后遗症</label>
    <description>强烈肾上腺素应激爆发后的崩溃与脱水疲劳期。由于身体机能极度透支以及乳酸的大量堆积，小人的运动能力、操作精度及意识会明显下降，并且创伤的炎性反应使得痛觉感受器变得异常敏感。</description>
    <hediffClass>EmergencyExpanded.Hediff_PercentageDisplay</hediffClass>
    <defaultLabelColor>(0.5, 0.4, 0.4)</defaultLabelColor>
    <maxSeverity>1.0</maxSeverity>
    <initialSeverity>1.0</initialSeverity>
    <comps>
      <li Class="HediffCompProperties_SeverityPerDay">
        <severityPerDay>-8.0</severityPerDay>
      </li>
    </comps>
    <stages>
      <li>
        <label>逐步缓释</label>
        <painOffset>0.05</painOffset>
        <capMods>
          <li><capacity>Consciousness</capacity><offset>-0.02</offset></li>
          <li><capacity>Moving</capacity><offset>-0.05</offset></li>
          <li><capacity>Manipulation</capacity><offset>-0.05</offset></li>
        </capMods>
      </li>
      <li>
        <minSeverity>0.5</minSeverity>
        <label>重度脱水疲劳</label>
        <painOffset>0.10</painOffset>
        <capMods>
          <li><capacity>Consciousness</capacity><offset>-0.05</offset></li>
          <li><capacity>Moving</capacity><offset>-0.10</offset></li>
          <li><capacity>Manipulation</capacity><offset>-0.10</offset></li>
        </capMods>
      </li>
    </stages>
  </HediffDef>

  <HediffDef ParentName="InjuryBase">
    <defName>EE_ClosedFracture</defName>
    <label>闭合性骨折</label>
    <labelNoun>闭合性骨折的伤口</labelNoun>
    <description>骨骼断裂但皮肤完整。导致剧烈疼痛和严重的肢体功能损耗。如果不进行固定就移动，会造成内部肌肉血管二次损伤，甚至错位导致畸形愈合。</description>
    <hediffClass>EmergencyExpanded.Hediff_Fracture</hediffClass>
    <injuryProps>
      <painPerSeverity>0.04</painPerSeverity>
      <canMerge>false</canMerge>
      <destroyedLabel>彻底粉碎</destroyedLabel>
    </injuryProps>
  </HediffDef>

  <HediffDef ParentName="InjuryBase">
    <defName>EE_OpenFracture</defName>
    <label>开放性骨折</label>
    <labelNoun>开放性骨折的伤口</labelNoun>
    <description>碎骨刺穿皮肤外露。伴随剧烈疼痛、大出血以及极高的伤口感染概率。需要立即进行野外紧急夹板固定并回院手术。</description>
    <hediffClass>EmergencyExpanded.Hediff_Fracture</hediffClass>
    <comps>
      <li Class="HediffCompProperties_TendDuration">
        <labelTendedWell>bandaged</labelTendedWell>
        <labelTendedWellInner>sutured</labelTendedWellInner>
        <labelSolidTendedWell>treated</labelSolidTendedWell>
      </li>
      <li Class="HediffCompProperties_Infecter">
        <infectionChance>0.60</infectionChance>
      </li>
    </comps>
    <injuryProps>
      <painPerSeverity>0.06</painPerSeverity>
      <bleedRate>1.5</bleedRate>
      <canMerge>false</canMerge>
      <destroyedLabel>彻底粉碎</destroyedLabel>
    </injuryProps>
  </HediffDef>

  <HediffDef>
    <defName>EE_Malunion</defName>
    <label>畸形愈合</label>
    <description>骨折后未经过正确的复位固定而愈合，碎骨以错误的姿态长死。使肢体效率永久下降，并伴随慢性疼痛。只能通过畸形接骨重折术进行物理打断并重置治疗。</description>
    <hediffClass>EmergencyExpanded.Hediff_PercentageDisplay</hediffClass>
    <defaultLabelColor>(0.8, 0.4, 0.4)</defaultLabelColor>
    <stages>
      <li>
        <painOffset>0.10</painOffset>
        <partEfficiencyOffset>-0.30</partEfficiencyOffset>
      </li>
    </stages>
  </HediffDef>
  <HediffDef>
    <defName>Coagulopathy</defName>
    <label>凝血功能障碍</label>
    <description>由于严重创伤、失血、失温以及酸中毒引发的致命三联征之一。凝血酶活性被严重抑制，伤口将极难自然愈合，且失血速度显著加快。</description>
    <hediffClass>EmergencyExpanded.Hediff_PercentageDisplay</hediffClass>
    <defaultLabelColor>(0.8, 0.2, 0.2)</defaultLabelColor>
    <maxSeverity>1.0</maxSeverity>
    <initialSeverity>0.1</initialSeverity>
    <comps>
      <li Class="EmergencyExpanded.HediffCompProperties_Coagulopathy" />
    </comps>
    <stages>
      <li>
        <label>轻度</label>
        <statOffsets>
          <MedicalTendQuality>-0.15</MedicalTendQuality>
        </statOffsets>
      </li>
      <li>
        <minSeverity>0.4</minSeverity>
        <label>中度</label>
        <statOffsets>
          <MedicalTendQuality>-0.3</MedicalTendQuality>
        </statOffsets>
      </li>
      <li>
        <minSeverity>0.7</minSeverity>
        <label>重度</label>
        <lifeThreatening>true</lifeThreatening>
        <statOffsets>
          <MedicalTendQuality>-0.5</MedicalTendQuality>
        </statOffsets>
      </li>
    </stages>
  </HediffDef>

  <HediffDef>
    <defName>SIRS</defName>
    <label>全身炎症反应综合征</label>
    <description>大面积组织损伤引发的海量炎症因子释放，导致全身毛细血管扩张与通透性增加。这是多脏器功能障碍的前奏。</description>
    <hediffClass>EmergencyExpanded.Hediff_PercentageDisplay</hediffClass>
    <defaultLabelColor>(0.8, 0.4, 0.1)</defaultLabelColor>
    <maxSeverity>1.0</maxSeverity>
    <initialSeverity>0.1</initialSeverity>
    <comps>
      <li Class="EmergencyExpanded.HediffCompProperties_SIRS" />
    </comps>
    <stages>
      <li>
        <label>早期</label>
        <capMods>
          <li><capacity>BloodPumping</capacity><offset>-0.1</offset></li>
        </capMods>
      </li>
      <li>
        <minSeverity>0.4</minSeverity>
        <label>进展期</label>
        <capMods>
          <li><capacity>BloodPumping</capacity><offset>-0.2</offset></li>
          <li><capacity>Consciousness</capacity><offset>-0.1</offset></li>
        </capMods>
      </li>
      <li>
        <minSeverity>0.7</minSeverity>
        <label>晚期 (微循环衰竭)</label>
        <lifeThreatening>true</lifeThreatening>
        <capMods>
          <li><capacity>BloodPumping</capacity><setMax>0.6</setMax></li>
          <li><capacity>Consciousness</capacity><setMax>0.6</setMax></li>
        </capMods>
      </li>
    </stages>
  </HediffDef>

  <HediffDef>
    <defName>MultipleOrganFailure</defName>
    <label>多器官功能衰竭</label>
    <description>长时间极低灌注与微循环崩溃导致的不可逆多脏器实质性缺血坏死。如果不迅速扭转循环状态，身体各器官将逐一停工直至死亡。</description>
    <hediffClass>EmergencyExpanded.Hediff_HiddenMultipleOrganFailure</hediffClass>
    <defaultLabelColor>(0.6, 0.2, 0.8)</defaultLabelColor>
    <maxSeverity>1.0</maxSeverity>
    <initialSeverity>0.1</initialSeverity>
    <comps>
      <li Class="EmergencyExpanded.HediffCompProperties_MODS">
        <severityIncreasePerDay>3.0</severityIncreasePerDay>
        <severityDecreasePerDay>2.0</severityDecreasePerDay>
      </li>
    </comps>
    <stages>
      <li>
        <label>一期</label>
        <capMods>
          <li><capacity>BloodFiltration</capacity><offset>-0.2</offset></li>
          <li><capacity>Metabolism</capacity><offset>-0.2</offset></li>
        </capMods>
      </li>
      <li>
        <minSeverity>0.4</minSeverity>
        <label>二期</label>
        <lifeThreatening>true</lifeThreatening>
        <capMods>
          <li><capacity>BloodFiltration</capacity><setMax>0.5</setMax></li>
          <li><capacity>Metabolism</capacity><setMax>0.5</setMax></li>
        </capMods>
      </li>
      <li>
        <minSeverity>0.8</minSeverity>
        <label>终末期</label>
        <lifeThreatening>true</lifeThreatening>
        <capMods>
          <li><capacity>BloodFiltration</capacity><setMax>0.1</setMax></li>
          <li><capacity>Metabolism</capacity><setMax>0.1</setMax></li>
          <li><capacity>BloodPumping</capacity><setMax>0.2</setMax></li>
          <li><capacity>Consciousness</capacity><setMax>0.1</setMax></li>
        </capMods>
      </li>
    </stages>
  </HediffDef>

  <HediffDef>
    <defName>EE_CPR_Receiving</defName>
    <label>心肺复苏中</label>
    <description>该伤员正在接受持续的人工心肺复苏（CPR）。胸外按压与人工呼吸为其脑部和核心器官提供了最基础的微循环灌注，冻结了脑缺氧与脑损伤的恶化，并能大幅度提高除颤成功率。医生一旦停手该状态将迅速消退。</description>
    <hediffClass>HediffWithComps</hediffClass>
    <defaultLabelColor>(0.2, 0.8, 0.8)</defaultLabelColor>
    <maxSeverity>1.0</maxSeverity>
    <initialSeverity>1.0</initialSeverity>
    <comps>
      <li Class="HediffCompProperties_Disappears">
        <disappearsAfterTicks>120</disappearsAfterTicks> <!-- 2秒无按压自动消退 -->
        <showRemainingTime>false</showRemainingTime>
      </li>
    </comps>
  </HediffDef>
</Defs>